{
    "$schema": "./restaurants.schema.json",
    "view": {
        "bounds": [
            [
                21.968091779843157,
                120.75775567912754
            ],
            [
                24.79758524206006,
                120.99813288368597
            ]
        ]
    },
    "items": [
        {
            "name": "墾丁海中天餐廳/團體合菜",
            "lat": 21.968091779843157,
            "lng": 120.75775567912754,
            "tier": 0,
            "priceBucket": 0,
            "address": "946屏東縣恆春鎮南灣路仁愛巷65號",
            "notes": "頂中頂 溫體西瓜 熟食生魚片",
            "tags": [
                "小吃",
                "麵食"
            ]
        },
        {
            "name": "肥仔龍鐵板燒",
            "lat": 24.79758524206006,
            "lng": 120.99813288368597,
            "tier": 5,
            "priceBucket": 200,
            "address": "300新竹市東區建功一路44號",
            "notes": "食物不難吃 真正影響食慾的是環境衛生",
            "tags": [
                "小吃"
            ]
        }
    ]
}
